leashline/__init__.py
leashline-0.1.1.dist-info/METADATA
leashline-0.1.1.dist-info/WHEEL
leashline-0.1.1.dist-info/licenses/LICENSE
leashline-0.1.1.dist-info/RECORD
