Metadata-Version: 2.4
Name: leashline
Version: 0.1.1
Summary: local-first dog escape detection.
Project-URL: Homepage, https://github.com/zgazak/leashline
Project-URL: Issues, https://github.com/zgazak/leashline/issues
License-Expression: MIT
License-File: LICENSE
Requires-Python: >=3.11
